{"namedChunkGroups":{"polyfill":{"name":"polyfill","assets":[{"name":"webpack-runtime-5c96ad7154ca7f8406ed.js","size":4761},{"name":"polyfill-ea100fe6f02bbc648246.js","size":82653}],"filteredAssets":0,"assetsSize":87414,"filteredAuxiliaryAssets":2,"auxiliaryAssetsSize":223137},"app":{"name":"app","assets":[{"name":"webpack-runtime-5c96ad7154ca7f8406ed.js","size":4761},{"name":"framework-a41a30b6052f08f79325.js","size":129775},{"name":"styles.e09da2b35e7e5b09dcea.css","size":20824},{"name":"app-5ef76962563fc730e878.js","size":69759}],"filteredAssets":0,"assetsSize":225119,"filteredAuxiliaryAssets":3,"auxiliaryAssetsSize":666673},"component---src-pages-404-js":{"name":"component---src-pages-404-js","assets":[{"name":"commons-6b55aec18e3721774323.js","size":29414},{"name":"component---src-pages-404-js-e0ec45fbb4e8deb48197.js","size":1978}],"filteredAssets":0,"assetsSize":31392,"filteredAuxiliaryAssets":2,"auxiliaryAssetsSize":92696},"component---src-pages-contact-js":{"name":"component---src-pages-contact-js","assets":[{"name":"commons-6b55aec18e3721774323.js","size":29414},{"name":"component---src-pages-contact-js-1fab66dbb88e5584acd0.js","size":3033}],"filteredAssets":0,"assetsSize":32447,"filteredAuxiliaryAssets":2,"auxiliaryAssetsSize":95529},"component---src-pages-docs-js":{"name":"component---src-pages-docs-js","assets":[{"name":"commons-6b55aec18e3721774323.js","size":29414},{"name":"component---src-pages-docs-js-67fa91ac30338c9880f8.js","size":2651}],"filteredAssets":0,"assetsSize":32065,"filteredAuxiliaryAssets":2,"auxiliaryAssetsSize":95101},"component---src-pages-docs-legacy-js":{"name":"component---src-pages-docs-legacy-js","assets":[{"name":"commons-6b55aec18e3721774323.js","size":29414},{"name":"component---src-pages-docs-legacy-js-10796a4c1fd591d456eb.js","size":2596}],"filteredAssets":0,"assetsSize":32010,"filteredAuxiliaryAssets":2,"auxiliaryAssetsSize":95143},"component---src-pages-getting-started-js":{"name":"component---src-pages-getting-started-js","assets":[{"name":"commons-6b55aec18e3721774323.js","size":29414},{"name":"component---src-pages-getting-started-js-8bee910980a8f7b81b5d.js","size":4841}],"filteredAssets":0,"assetsSize":34255,"filteredAuxiliaryAssets":2,"auxiliaryAssetsSize":99011},"component---src-pages-help-js":{"name":"component---src-pages-help-js","assets":[{"name":"commons-6b55aec18e3721774323.js","size":29414},{"name":"component---src-pages-help-js-0f0ae156468f7adc4d0e.js","size":8119}],"filteredAssets":0,"assetsSize":37533,"filteredAuxiliaryAssets":3,"auxiliaryAssetsSize":122632},"component---src-pages-index-js":{"name":"component---src-pages-index-js","assets":[{"name":"commons-6b55aec18e3721774323.js","size":29414},{"name":"component---src-pages-index-js-ecd2dbf86e76b17f934b.js","size":10408}],"filteredAssets":0,"assetsSize":39822,"filteredAuxiliaryAssets":4,"auxiliaryAssetsSize":182939},"component---src-pages-markdown-remark-frontmatter-slug-js":{"name":"component---src-pages-markdown-remark-frontmatter-slug-js","assets":[{"name":"commons-6b55aec18e3721774323.js","size":29414},{"name":"component---src-pages-markdown-remark-frontmatter-slug-js-ef449f8cc21bec58716d.js","size":1121}],"filteredAssets":0,"assetsSize":30535,"filteredAuxiliaryAssets":2,"auxiliaryAssetsSize":92112},"component---src-pages-news-js":{"name":"component---src-pages-news-js","assets":[{"name":"commons-6b55aec18e3721774323.js","size":29414},{"name":"component---src-pages-news-js-e3ac4307eb8ba875ce8d.js","size":1862}],"filteredAssets":0,"assetsSize":31276,"filteredAuxiliaryAssets":2,"auxiliaryAssetsSize":93683},"component---src-pages-security-policy-js":{"name":"component---src-pages-security-policy-js","assets":[{"name":"commons-6b55aec18e3721774323.js","size":29414},{"name":"component---src-pages-security-policy-js-fcc8be3f84e910fe6dce.js","size":7334}],"filteredAssets":0,"assetsSize":36748,"filteredAuxiliaryAssets":2,"auxiliaryAssetsSize":99495},"component---src-pages-talks-js":{"name":"component---src-pages-talks-js","assets":[{"name":"commons-6b55aec18e3721774323.js","size":29414},{"name":"component---src-pages-talks-js-3b3331b17f1c36714804.js","size":19025}],"filteredAssets":0,"assetsSize":48439,"filteredAuxiliaryAssets":2,"auxiliaryAssetsSize":116411},"component---src-pages-technical-charter-js":{"name":"component---src-pages-technical-charter-js","assets":[{"name":"commons-6b55aec18e3721774323.js","size":29414},{"name":"component---src-pages-technical-charter-js-01efff6d58367ca9e9a8.js","size":13907}],"filteredAssets":0,"assetsSize":43321,"filteredAuxiliaryAssets":2,"auxiliaryAssetsSize":106245},"component---src-pages-usecases-js":{"name":"component---src-pages-usecases-js","assets":[{"name":"commons-6b55aec18e3721774323.js","size":29414},{"name":"component---src-pages-usecases-js-7b58a32129226db6c75d.js","size":12320}],"filteredAssets":0,"assetsSize":41734,"filteredAuxiliaryAssets":2,"auxiliaryAssetsSize":107243},"component---src-pages-using-typescript-tsx":{"name":"component---src-pages-using-typescript-tsx","assets":[{"name":"commons-6b55aec18e3721774323.js","size":29414},{"name":"component---src-pages-using-typescript-tsx-5988e924f0656f598cc2.js","size":1333}],"filteredAssets":0,"assetsSize":30747,"filteredAuxiliaryAssets":2,"auxiliaryAssetsSize":91775}},"assetsByChunkName":{"polyfill":["webpack-runtime-5c96ad7154ca7f8406ed.js","polyfill-ea100fe6f02bbc648246.js"],"app":["webpack-runtime-5c96ad7154ca7f8406ed.js","framework-a41a30b6052f08f79325.js","styles.e09da2b35e7e5b09dcea.css","app-5ef76962563fc730e878.js"],"component---src-pages-404-js":["commons-6b55aec18e3721774323.js","component---src-pages-404-js-e0ec45fbb4e8deb48197.js"],"component---src-pages-contact-js":["commons-6b55aec18e3721774323.js","component---src-pages-contact-js-1fab66dbb88e5584acd0.js"],"component---src-pages-docs-js":["commons-6b55aec18e3721774323.js","component---src-pages-docs-js-67fa91ac30338c9880f8.js"],"component---src-pages-docs-legacy-js":["commons-6b55aec18e3721774323.js","component---src-pages-docs-legacy-js-10796a4c1fd591d456eb.js"],"component---src-pages-getting-started-js":["commons-6b55aec18e3721774323.js","component---src-pages-getting-started-js-8bee910980a8f7b81b5d.js"],"component---src-pages-help-js":["commons-6b55aec18e3721774323.js","component---src-pages-help-js-0f0ae156468f7adc4d0e.js"],"component---src-pages-index-js":["commons-6b55aec18e3721774323.js","component---src-pages-index-js-ecd2dbf86e76b17f934b.js"],"component---src-pages-markdown-remark-frontmatter-slug-js":["commons-6b55aec18e3721774323.js","component---src-pages-markdown-remark-frontmatter-slug-js-ef449f8cc21bec58716d.js"],"component---src-pages-news-js":["commons-6b55aec18e3721774323.js","component---src-pages-news-js-e3ac4307eb8ba875ce8d.js"],"component---src-pages-security-policy-js":["commons-6b55aec18e3721774323.js","component---src-pages-security-policy-js-fcc8be3f84e910fe6dce.js"],"component---src-pages-talks-js":["commons-6b55aec18e3721774323.js","component---src-pages-talks-js-3b3331b17f1c36714804.js"],"component---src-pages-technical-charter-js":["commons-6b55aec18e3721774323.js","component---src-pages-technical-charter-js-01efff6d58367ca9e9a8.js"],"component---src-pages-usecases-js":["commons-6b55aec18e3721774323.js","component---src-pages-usecases-js-7b58a32129226db6c75d.js"],"component---src-pages-using-typescript-tsx":["commons-6b55aec18e3721774323.js","component---src-pages-using-typescript-tsx-5988e924f0656f598cc2.js"]},"childAssetsByChunkName":{}}